data_memory.v
module data_memory (
    input clk,
    input mem_read,
    input mem_write,
    input [31:0] address,
    input [31:0] write_data,
    output [31:0] read_data
);
    reg [31:0] memory [0:2047]; // 2048 words of 32-bit memory
    integer i;

    initial begin
        // Initialize everything to zero first
        for (i = 0; i < 2048; i = i + 1) begin
            memory[i] = 32'b0;
        end

        // Initialize input array (arr) with floating point values
        memory[0] = 32'h3DFBF0BE; // 0.123 in IEEE 754 format
        memory[1] = 32'h3E8BF7CF; // 0.2735
        memory[2] = 32'h3E300000; // 0.172
        memory[3] = 32'h3EB4978D; // 0.3532
        memory[4] = 32'h3E11EB85; // 0.1425
        memory[5] = 32'h3F0BA5E3; // 0.5456
        memory[6] = 32'h3E5B0F28; // 0.214
        memory[7] = 32'h3F78F5C3; // 0.972

        // Initialize ten constant at indices memory location
        memory[100] = 32'h41200000; // 10.0 in IEEE 754 format

        // Initialize indices memory (for counting elements in each bucket)
        for (i = 100; i < 110; i = i + 1) begin
            memory[i] = 32'h0;  // Initialize indices to 0
        end

        // Initialize temp array (for buckets)
        for (i = 200; i < 300; i = i + 1) begin
            memory[i] = 32'h0;  // Initialize temp array to 0
        end
    end

    assign read_data = (mem_read) ? memory[address[11:2]] : 32'bz;

    always @(posedge clk) begin
        if (mem_write)
            memory[address[11:2]] <= write_data;
    end
endmodule

alu.v
module alu (
    input [31:0] input1,
    input [31:0] input2,
    input [3:0] alu_control,
    output reg [31:0] result,
    output zero,
    
    // Additional floating-point outputs
    output reg fp_compare_result
);
    assign zero = (result == 0);
    
    // For IEEE 754 floating-point operations
    reg sign1, sign2, sign_result;
    reg [7:0] exp1, exp2, exp_result;
    reg [23:0] mant1, mant2;
    reg [47:0] mant_product;
    
    always @(*) begin
        // Initialize IEEE 754 components when doing FP operations
        if (alu_control[3:2] == 2'b11) begin
            sign1 = input1[31];
            sign2 = input2[31];
            exp1 = input1[30:23];
            exp2 = input2[30:23];
            mant1 = {1'b1, input1[22:0]}; // Add implicit leading 1
            mant2 = {1'b1, input2[22:0]};
        end
        
        case (alu_control)
            // Integer ALU operations
            4'b0000: result = input1 & input2;                   // AND
            4'b0001: result = input1 | input2;                   // OR
            4'b0010: result = input1 + input2;                   // ADD
            4'b0110: result = input1 - input2;                   // SUB
            4'b0111: result = (input1 < input2) ? 1 : 0;         // SLT
            4'b1000: result = input1 << input2[4:0];             // SLL
            4'b1001: result = input1 >> input2[4:0];             // SRL
            4'b1010: result = input1 ^ input2;                   // XOR
            4'b1011: result = ~(input1 | input2);                // NOR
            
            // Floating-point ALU operations
            4'b1100: begin // MUL.S - IEEE 754 floating-point multiplication
                // Calculate sign: XOR of input signs
                sign_result = sign1 ^ sign2;
                
                // Calculate exponent: Add exponents and subtract bias (127)
                exp_result = exp1 + exp2 - 8'd127;
                
                // Multiply mantissas
                mant_product = mant1 * mant2;
                
                // Normalize (adjust exponent and mantissa)
                if (mant_product[47]) begin
                    // Shift right by 1 and increment exponent
                    mant_product = mant_product >> 1;
                    exp_result = exp_result + 8'd1;
                end
                
                // Assemble result
                result = {sign_result, exp_result, mant_product[46:24]};
            end
            
            4'b1101: begin // ADD.S - IEEE 754 floating-point addition
                // Simplified implementation - would need full IEEE 754 handling
                // Align exponents, add mantissas, normalize, etc.
                result = input1; // Placeholder
            end
            
            4'b1110: begin // C.EQ.S - Floating-point compare equal
                fp_compare_result = (input1 == input2);
                result = 32'b0; // Result not used for comparison operations
            end
            
            4'b1111: begin // C.LT.S - Floating-point compare less than
                // Compare sign bits first
                if (sign1 && !sign2) begin
                    fp_compare_result = 1; // Negative < Positive
                end 
                else if (!sign1 && sign2) begin
                    fp_compare_result = 0; // Positive > Negative
                end
                else if (!sign1 && !sign2) begin
                    // Both positive, compare magnitude
                    fp_compare_result = (exp1 < exp2) || 
                                       ((exp1 == exp2) && (mant1 < mant2));
                end
                else begin
                    // Both negative, compare magnitude (reversed)
                    fp_compare_result = (exp1 > exp2) || 
                                       ((exp1 == exp2) && (mant1 > mant2));
                end
                result = 32'b0; // Result not used for comparison operations
            end
            
            default: result = 0;
        endcase
    end
endmodule

alu_control.v
module alu_control (
    input [1:0] alu_op,
    input [5:0] funct,
    input fp_operation,
    output reg [3:0] alu_control
);
    always @(*) begin
        if (fp_operation) begin
            // Floating-point operations
            case(funct)
                6'b000000: alu_control = 4'b1101; // ADD.S
                6'b000001: alu_control = 4'b1101; // SUB.S (using ADD.S code as placeholder)
                6'b000010: alu_control = 4'b1100; // MUL.S
                6'b000100: alu_control = 4'b1110; // C.EQ.S
                6'b000110: alu_control = 4'b1111; // C.LT.S
                default:   alu_control = 4'b0000; // Default operation
            endcase
        end
        else begin
            case(alu_op)
                2'b00: alu_control = 4'b0010; // Add for load/store
                2'b01: alu_control = 4'b0110; // Subtract for branch
                2'b10: begin
                    // R-type instructions
                    case(funct)
                        6'b100000: alu_control = 4'b0010; // ADD
                        6'b100010: alu_control = 4'b0110; // SUB
                        6'b100100: alu_control = 4'b0000; // AND
                        6'b100101: alu_control = 4'b0001; // OR
                        6'b101010: alu_control = 4'b0111; // SLT
                        6'b000000: alu_control = 4'b1000; // SLL
                        6'b000010: alu_control = 4'b1001; // SRL
                        6'b100110: alu_control = 4'b1010; // XOR
                        6'b100111: alu_control = 4'b1011; // NOR
                        default:   alu_control = 4'b0000; // Default operation
                    endcase
                end
                2'b11: begin
                    // I-type ALU operations
                    case(funct[5:3])
                        3'b001: alu_control = 4'b0000; // ANDI
                        3'b010: alu_control = 4'b0001; // ORI
                        3'b011: alu_control = 4'b1010; // XORI
                        default: alu_control = 4'b0010; // ADDI (default)
                    endcase
                end
                default: alu_control = 4'b0000; // Default operation
            endcase
        end
    end
endmodule

fp_register_file.v
module fp_register_file (
    input clk,
    input fp_reg_write,
    input [4:0] read_reg1,
    input [4:0] read_reg2, 
    input [4:0] write_reg,
    input [31:0] write_data,
    output [31:0] read_data1,
    output [31:0] read_data2
);
    reg [31:0] fp_registers [0:31]; // 32 floating-point registers
    
    // Initialization
    integer i;
    initial begin
        for (i = 0; i < 32; i = i + 1) begin
            fp_registers[i] = 32'b0;
        end
    end
    
    // Read operations (asynchronous)
    assign read_data1 = fp_registers[read_reg1];
    assign read_data2 = fp_registers[read_reg2];
    
    // Write operation (synchronous)
    always @(posedge clk) begin
        if (fp_reg_write) begin
            fp_registers[write_reg] <= write_data;
            $display("FP REG WRITE: Reg=%d, Data=%h", write_reg, write_data);
        end
    end

    // Debug task to print register values
    task debug_registers;
        integer i;
        begin
            for (i = 0; i < 32; i = i + 1) begin
                $display("FP Register[%0d]: %h", i, fp_registers[i]);
            end
        end
    endtask
endmodule

register_file.v
module register_file (
    input clk,
    input reg_write,
    input [4:0] read_reg1,
    input [4:0] read_reg2,
    input [4:0] write_reg,
    input [31:0] write_data,
    output [31:0] read_data1,
    output [31:0] read_data2
);
    reg [31:0] registers [0:31];

    // Read operations
    assign read_data1 = registers[read_reg1];
    assign read_data2 = registers[read_reg2];

    // Write operation
    always @(posedge clk) begin
        if (reg_write)
            registers[write_reg] <= write_data;
    end
endmodule

control_unit.v
module control_unit (
    input [5:0] opcode,
    input [5:0] funct,
    output reg reg_dst,
    output reg alu_src,
    output reg mem_to_reg,
    output reg reg_write,
    output reg mem_read,
    output reg mem_write,
    output reg branch,
    output reg [1:0] alu_op,
    
    // Additional control signals
    output reg jump,
    output reg fp_reg_write,
    output reg fp_reg_read,
    output reg fp_operation,
    output reg move_fp_to_cpu,
    output reg move_cpu_to_fp
);
    // R-type instructions
    parameter R_TYPE = 6'b000000;
    
    // Memory instructions
    parameter LW = 6'b100011;
    parameter SW = 6'b101011;
    
    // Branch instructions
    parameter BEQ = 6'b000100;
    parameter BNE = 6'b000101;
    parameter J = 6'b000010;
    
    // Immediate instructions
    parameter ADDI = 6'b001000;
    parameter ANDI = 6'b001100;
    parameter ORI = 6'b001101;
    parameter XORI = 6'b001110;
    parameter LUI = 6'b001111;
    
    // Floating-point instructions
    parameter LWC1 = 6'b110001;
    parameter SWC1 = 6'b111001;
    parameter CP1 = 6'b010001;
    
    always @(*) begin
        // Default values
        reg_dst = 0;
        alu_src = 0;
        mem_to_reg = 0;
        reg_write = 0;
        mem_read = 0;
        mem_write = 0;
        branch = 0;
        alu_op = 2'b00;
        jump = 0;
        fp_reg_write = 0;
        fp_reg_read = 0;
        fp_operation = 0;
        move_fp_to_cpu = 0;
        move_cpu_to_fp = 0;
        
        case(opcode)
            R_TYPE: begin
                reg_dst = 1;
                reg_write = 1;
                alu_op = 2'b10;
            end
            
            LW: begin
                alu_src = 1;
                mem_to_reg = 1;
                reg_write = 1;
                mem_read = 1;
            end
            
            SW: begin
                alu_src = 1;
                mem_write = 1;
            end
            
            BEQ: begin
                branch = 1;
                alu_op = 2'b01;
            end
            
            BNE: begin
                branch = 1;
                alu_op = 2'b01;
                // Additional control for BNE vs BEQ
            end
            
            J: begin
                jump = 1;
            end
            
            ADDI: begin
                alu_src = 1;
                reg_write = 1;
            end
            
            ANDI: begin
                alu_src = 1;
                reg_write = 1;
                alu_op = 2'b11;
            end
            
            ORI: begin
                reg_dst = 0;
                alu_src = 1;
                reg_write = 1;
                mem_to_reg = 0;
                alu_op = 2'b11; // Special ALU op for OR
            end
            
            XORI: begin
                alu_src = 1;
                reg_write = 1;
            end
            
            LUI: begin
                reg_dst = 0;
                alu_src = 1;
                reg_write = 1;
                mem_to_reg = 0;
                // Special LUI handling
            end
            
            // Floating-point instructions
            LWC1: begin
                alu_src = 1;
                mem_read = 1;
                fp_reg_write = 1;
                mem_to_reg = 0; // Important: Data comes from memory, not ALU
            end
            
            SWC1: begin
                alu_src = 1;
                mem_write = 1;
                fp_reg_read = 1;
            end
            
            CP1: begin
                // Decode CP1 instructions based on the rs field (instruction[25:21])
                case(funct)
                    // MFC1: Move From Coprocessor 1
                    6'b000000: begin
                        reg_write = 1;
                        move_fp_to_cpu = 1;
                    end
                    
                    // MTC1: Move To Coprocessor 1
                    6'b000100: begin
                        fp_reg_write = 1;
                        move_cpu_to_fp = 1;
                    end
                    
                    // Floating-point operations
                    default: begin
                        fp_operation = 1;
                        fp_reg_write = 1;
                    end
                endcase
            end
            
            default: begin
                // Default values already set
            end
        endcase
    end
endmodule

instruction_memory.v
module instruction_memory (
    input [31:0] address,
    output [31:0] instruction
);
    reg [31:0] memory [0:1023]; // 1024 words of 32-bit memory

    initial begin
        // Basic setup - Get array pointers
        memory[0] = 32'h3C100000; // lui $s0, 0x0000    # Load address of arr
        memory[1] = 32'h36100000; // ori $s0, $s0, 0x0  # Complete arr address
        memory[2] = 32'h3C110000; // lui $s1, 0x0000    # Load address of temp
        memory[3] = 32'h36310200; // ori $s1, $s1, 0x200 # Complete temp address (0x200)
        memory[4] = 32'h3C120000; // lui $s2, 0x0000    # Load address of indices
        memory[5] = 32'h36520100; // ori $s2, $s2, 0x100 # Complete indices address (0x100)
        memory[6] = 32'h8E4A0064; // lwc1 $f10, 100($s2) # Load float 10.0
        memory[7] = 32'h20080000; // addi $t0, $zero, 0 # counter = 0
        memory[8] = 32'h20090000; // addi $t1, $zero, 0 # array counter = 0
        memory[9] = 32'hC1080000; // lwc1 $f0, 0($t0)   # Load array element
        memory[10] = 32'h46000086; // mov.s $f2, $f0    # Copy value
        memory[11] = 32'h460A0002; // mul.s $f0, $f0, $f10 # Multiply by 10
        memory[12] = 32'h4600010D; // trunc.w.s $f0, $f0 # Convert to integer
        memory[13] = 32'h44020000; // mfc1 $v0, $f0     # Move to integer register
        memory[14] = 32'h00025821; // addu $t3, $zero, $v0 # Copy to $t3
        memory[15] = 32'h000250C0; // sll $t2, $v0, 3   # Multiply by 8
        memory[16] = 32'h000254C0; // sll $t2, $v0, 19  # Multiply by 32
        memory[17] = 32'h01485020; // add $t2, $t2, $t0 # Add to get 40*value
        memory[18] = 32'h01515020; // add $t2, $t2, $s1 # Add temp base address
        memory[19] = 32'h000B5880; // sll $t3, $t3, 2   # Multiply index by 4
        memory[20] = 32'h01725820; // add $t3, $t3, $s2 # Add indices base
        memory[21] = 32'h8D6C0000; // lw $t4, 0($t3)    # Load current count
        memory[22] = 32'h218C0001; // addi $t4, $t4, 1  # Increment count
        memory[23] = 32'hAD6C0000; // sw $t4, 0($t3)    # Store updated count
        memory[24] = 32'h218CFFFF; // addi $t4, $t4, -1 # Adjust back by 1
        memory[25] = 32'h000C6080; // sll $t4, $t4, 2   # Multiply by 4
        memory[26] = 32'h018A6020; // add $t4, $t4, $t2 # Add to bucket base
        memory[27] = 32'hE58C0000; // swc1 $f2, 0($t4)  # Store in bucket
        memory[28] = 32'h21290001; // addi $t1, $t1, 1  # Increment array counter
        memory[29] = 32'h21080004; // addi $t0, $t0, 4  # Advance element pointer
        memory[30] = 32'h1528FFED; // bne $t1, $t0, temp_maker # Loop until done
        memory[31] = 32'h2002000A; // addi $v0, $zero, 10 # Exit syscall code
        memory[32] = 32'h0000000C; // syscall           # Exit program
    end

    assign instruction = memory[address[11:2]]; // Word-aligned access
endmodule

pc_register.v
module pc_register (
    input clk,
    input reset,
    input [31:0] pc_in,
    output reg [31:0] pc_out
);
    always @(posedge clk or posedge reset) begin
        if (reset)
            pc_out <= 32'b0; // Reset PC to 0
        else
            pc_out <= pc_in; // Update PC
    end
endmodule

iitk_mini_mips.v
module iitk_mini_mips (
    input clk,
    input reset
);
    // Wires for existing components
    wire [31:0] pc_in, pc_out, instruction, read_data1, read_data2, alu_result, mem_data;
    wire [31:0] sign_ext_imm, alu_input2;
    wire [4:0] write_reg, fp_write_reg;
    wire [3:0] alu_control;
    wire reg_dst, alu_src, mem_to_reg, reg_write, mem_read, mem_write, branch, zero;
    wire [1:0] alu_op; // Fix: Ensure alu_op is 2 bits wide
    
    // Additional wires for new features
    wire jump, fp_reg_write, fp_reg_read, fp_operation, move_fp_to_cpu, move_cpu_to_fp;
    wire [31:0] fp_read_data1, fp_read_data2, fp_write_data;
    wire fp_compare_result;
    
    // PC
    pc_register pc_inst (
        .clk(clk),
        .reset(reset),
        .pc_in(pc_in),
        .pc_out(pc_out)
    );

    // Instruction Memory
    instruction_memory im_inst (
        .address(pc_out),
        .instruction(instruction)
    );

    // Enhanced Control Unit
    control_unit cu_inst (
        .opcode(instruction[31:26]),
        .funct(instruction[5:0]),
        .reg_dst(reg_dst),
        .alu_src(alu_src),
        .mem_to_reg(mem_to_reg),
        .reg_write(reg_write),
        .mem_read(mem_read),
        .mem_write(mem_write),
        .branch(branch),
        .alu_op(alu_op),
        
        // New control signals
        .jump(jump),
        .fp_reg_write(fp_reg_write),
        .fp_reg_read(fp_reg_read),
        .fp_operation(fp_operation),
        .move_fp_to_cpu(move_fp_to_cpu),
        .move_cpu_to_fp(move_cpu_to_fp)
    );

    // Register File
    register_file rf_inst (
        .clk(clk),
        .reg_write(reg_write),
        .read_reg1(instruction[25:21]),
        .read_reg2(instruction[20:16]),
        .write_reg(write_reg),
        .write_data(
            move_fp_to_cpu ? fp_read_data1 : 
            mem_to_reg ? mem_data : alu_result
        ),
        .read_data1(read_data1),
        .read_data2(read_data2)
    );
    
    // Floating-Point Register File
    fp_register_file fp_rf_inst (
        .clk(clk),
        .fp_reg_write(fp_reg_write),
        .read_reg1(instruction[15:11]),  // fs field
        .read_reg2(instruction[20:16]),  // ft field
        .write_reg(instruction[10:6]),   // fd field
        .write_data(
            move_cpu_to_fp ? read_data1 : 
            (mem_to_reg ? mem_data : alu_result) // Fix: Ensure correct data source
        ),
        .read_data1(fp_read_data1),
        .read_data2(fp_read_data2)
    );

    // ALU Control
    alu_control alu_ctrl_inst (
        .alu_op(alu_op),
        .funct(instruction[5:0]),
        .fp_operation(fp_operation),
        .alu_control(alu_control)
    );

    // Extended ALU
    alu alu_inst (
        .input1(read_data1),
        .input2(alu_src ? sign_ext_imm : read_data2),
        .alu_control(alu_control),
        .result(alu_result),
        .zero(zero),
        .fp_compare_result(fp_compare_result)
    );

    // Data Memory
    data_memory dm_inst (
        .clk(clk),
        .mem_read(mem_read),
        .mem_write(mem_write),
        .address(alu_result),
        .write_data(
            fp_reg_read ? fp_read_data1 : 
            (move_cpu_to_fp ? read_data2 : read_data2) // Fix: Handle MTC1
        ),
        .read_data(mem_data)
    );

    // Sign Extend
    assign sign_ext_imm = {{16{instruction[15]}}, instruction[15:0]};

    // Write Register Selection
    assign write_reg = reg_dst ? instruction[15:11] : instruction[20:16];

    // PC Update Logic (enhanced with jump)
    assign pc_in = 
                   jump ? {pc_out[31:28], instruction[25:0], 2'b00} :
                   (branch & zero) ? pc_out + (sign_ext_imm << 2) :
                   pc_out + 4;

    // Debug logic to trace PC and instructions
    /*
    always @(posedge clk) begin
        if (!reset) begin
            $display("PC=%h, Instr=%h, OpCode=%b, Rs=%d, Rt=%d, Rd=%d", 
                     pc_out, instruction, instruction[31:26],
                     instruction[25:21], instruction[20:16], instruction[15:11]);
        end
    end
    */
endmodule

testbench_bucket_sort.v
`timescale 1ns / 1ps

module testbench_bucket_sort;
    // Inputs
    reg clk;
    reg reset;
    integer i, j, addr;
    integer instr_count;

    // Instantiate the IITK Mini MIPS processor
    iitk_mini_mips uut (
        .clk(clk),
        .reset(reset)
    );

    // Clock generation
    initial begin
        clk = 0;
        forever #5 clk = ~clk; // 10ns clock period
    end

    // Test sequence
    initial begin
        // Initialize variables
        instr_count = 0;
        
        // Generate VCD file for waveform viewing
        $dumpfile("bucket_sort.vcd");
        $dumpvars(0, testbench_bucket_sort);
        
        // Initialize inputs
        reset = 1;
        #20;
        reset = 0;
        
        // Display initial array
        $display("\n--- Initial Array (Hex Values) ---");
        for (i = 0; i < 8; i = i + 1) begin
            $display("Array[%0d]: %h", i, uut.dm_inst.memory[i]);
        end

        // Debug: Trace FP register writes
        $display("\n--- Floating-Point Register Values ---");
        uut.fp_rf_inst.debug_registers(); // Fix: Call debug task to print FP registers
        
        // Wait for initialization - show registers after setup
        #500;
        $display("\n--- Register Values After Setup ---");
        $display("$s0 (arr base): %h", uut.rf_inst.registers[16]);
        $display("$s1 (temp base): %h", uut.rf_inst.registers[17]);
        $display("$s2 (indices base): %h", uut.rf_inst.registers[18]);
        
        // Run for a while to allow sort to process
        #20000;
        
        // Display indices array
        $display("\n--- Bucket Indices ---");
        for (i = 0; i < 10; i = i + 1) begin
            $display("Bucket[%0d] Count: %d", i, uut.dm_inst.memory[100+i]);
        end
        
        // Display sorted array
        $display("\n--- Final Sorted Array (Hex Values) ---");
        for (i = 200; i < 208; i = i + 1) begin
            $display("Array[%0d]: %h", i - 200, uut.dm_inst.memory[i]);
        end
        
        // End simulation
        $finish;
    end
    
    // Add execution trace
    always @(posedge clk) begin
        if (!reset) begin
            instr_count = instr_count + 1;
            if (instr_count % 1000 == 0)
                $display("Executed %0d instructions...", instr_count);
        end
    end
endmodule

bucket_sort.vcd
$date
	Wed Apr 09 12:42:38 2025
$end
$version
	Icarus Verilog
$end
$timescale
	1ps
$end
$scope module testbench_bucket_sort $end
$var reg 1 ! clk $end
$var reg 1 " reset $end
$var integer 32 # i [31:0] $end
$var integer 32 $ instr_count [31:0] $end
$scope module uut $end
$var wire 1 ! clk $end
$var wire 1 " reset $end
$var wire 1 % zero $end
$var wire 5 & write_reg [4:0] $end
$var wire 32 ' sign_ext_imm [31:0] $end
$var wire 1 ( reg_write $end
$var wire 1 ) reg_dst $end
$var wire 32 * read_data2 [31:0] $end
$var wire 32 + read_data1 [31:0] $end
$var wire 32 , pc_out [31:0] $end
$var wire 32 - pc_in [31:0] $end
$var wire 1 . move_fp_to_cpu $end
$var wire 1 / move_cpu_to_fp $end
$var wire 1 0 mem_write $end
$var wire 1 1 mem_to_reg $end
$var wire 1 2 mem_read $end
$var wire 32 3 mem_data [31:0] $end
$var wire 1 4 jump $end
$var wire 32 5 instruction [31:0] $end
$var wire 1 6 fp_reg_write $end
$var wire 1 7 fp_reg_read $end
$var wire 32 8 fp_read_data2 [31:0] $end
$var wire 32 9 fp_read_data1 [31:0] $end
$var wire 1 : fp_operation $end
$var wire 1 ; fp_compare_result $end
$var wire 1 < branch $end
$var wire 1 = alu_src $end
$var wire 32 > alu_result [31:0] $end
$var wire 2 ? alu_op [1:0] $end
$var wire 4 @ alu_control [3:0] $end
$scope module alu_ctrl_inst $end
$var wire 6 A funct [5:0] $end
$var wire 1 : fp_operation $end
$var wire 2 B alu_op [1:0] $end
$var reg 4 C alu_control [3:0] $end
$upscope $end
$scope module alu_inst $end
$var wire 4 D alu_control [3:0] $end
$var wire 32 E input2 [31:0] $end
$var wire 1 % zero $end
$var wire 32 F input1 [31:0] $end
$var reg 8 G exp1 [7:0] $end
$var reg 8 H exp2 [7:0] $end
$var reg 8 I exp_result [7:0] $end
$var reg 1 ; fp_compare_result $end
$var reg 24 J mant1 [23:0] $end
$var reg 24 K mant2 [23:0] $end
$var reg 48 L mant_product [47:0] $end
$var reg 32 M result [31:0] $end
$var reg 1 N sign1 $end
$var reg 1 O sign2 $end
$var reg 1 P sign_result $end
$upscope $end
$scope module cu_inst $end
$var wire 6 Q funct [5:0] $end
$var wire 6 R opcode [5:0] $end
$var parameter 6 S ADDI $end
$var parameter 6 T ANDI $end
$var parameter 6 U BEQ $end
$var parameter 6 V BNE $end
$var parameter 6 W CP1 $end
$var parameter 6 X J $end
$var parameter 6 Y LUI $end
$var parameter 6 Z LW $end
$var parameter 6 [ LWC1 $end
$var parameter 6 \ ORI $end
$var parameter 6 ] R_TYPE $end
$var parameter 6 ^ SW $end
$var parameter 6 _ SWC1 $end
$var parameter 6 ` XORI $end
$var reg 2 a alu_op [1:0] $end
$var reg 1 = alu_src $end
$var reg 1 < branch $end
$var reg 1 : fp_operation $end
$var reg 1 7 fp_reg_read $end
$var reg 1 6 fp_reg_write $end
$var reg 1 4 jump $end
$var reg 1 2 mem_read $end
$var reg 1 1 mem_to_reg $end
$var reg 1 0 mem_write $end
$var reg 1 / move_cpu_to_fp $end
$var reg 1 . move_fp_to_cpu $end
$var reg 1 ) reg_dst $end
$var reg 1 ( reg_write $end
$upscope $end
$scope module dm_inst $end
$var wire 32 b address [31:0] $end
$var wire 1 ! clk $end
$var wire 1 2 mem_read $end
$var wire 1 0 mem_write $end
$var wire 32 c write_data [31:0] $end
$var wire 32 d read_data [31:0] $end
$var integer 32 e i [31:0] $end
$upscope $end
$scope module fp_rf_inst $end
$var wire 1 ! clk $end
$var wire 1 6 fp_reg_write $end
$var wire 32 f read_data1 [31:0] $end
$var wire 32 g read_data2 [31:0] $end
$var wire 5 h read_reg1 [4:0] $end
$var wire 5 i read_reg2 [4:0] $end
$var wire 32 j write_data [31:0] $end
$var wire 5 k write_reg [4:0] $end
$var integer 32 l i [31:0] $end
$scope task debug_registers $end
$var integer 32 m i [31:0] $end
$upscope $end
$upscope $end
$scope module im_inst $end
$var wire 32 n instruction [31:0] $end
$var wire 32 o address [31:0] $end
$upscope $end
$scope module pc_inst $end
$var wire 1 ! clk $end
$var wire 32 p pc_in [31:0] $end
$var wire 1 " reset $end
$var reg 32 q pc_out [31:0] $end
$upscope $end
$scope module rf_inst $end
$var wire 1 ! clk $end
$var wire 32 r read_data1 [31:0] $end
$var wire 32 s read_data2 [31:0] $end
$var wire 5 t read_reg1 [4:0] $end
$var wire 5 u read_reg2 [4:0] $end
$var wire 1 ( reg_write $end
$var wire 32 v write_data [31:0] $end
$var wire 5 w write_reg [4:0] $end
$upscope $end
$upscope $end
$upscope $end
$enddefinitions $end
$comment Show the parameter values. $end
$dumpall
b1110 `
b111001 _
b101011 ^
b0 ]
b1101 \
b110001 [
b100011 Z
b1111 Y
b10 X
b10001 W
b101 V
b100 U
b1100 T
b1000 S
$end
#0
$dumpvars
b10000 w
bx v
b10000 u
b0 t
bx s
bx r
b0 q
b100 p
b0 o
b111100000100000000000000000000 n
bx m
b100000 l
b0 k
bx j
b10000 i
b0 h
b0 g
b0 f
b100101100 e
bz d
bx c
bx b
b0 a
b1111 R
b0 Q
xP
xO
xN
bx M
bx L
bx K
bx J
bx I
bx H
bx G
bx F
b0 E
b10 D
b10 C
b0 B
b0 A
b10 @
b0 ?
bx >
1=
0<
x;
0:
b0 9
b0 8
07
06
b111100000100000000000000000000 5
04
bz 3
02
01
00
0/
0.
b100 -
b0 ,
bx +
bx *
0)
1(
b0 '
b10000 &
x%
b0 $
bx #
1"
0!
$end
#5000
1!
#10000
0!
#15000
1!
#20000
0!
b100000 m
b1000 #
0"
#25000
b11 ?
b11 B
b11 a
1(
1=
b10000 t
b1101 R
b1000 -
b1000 p
b110110000100000000000000000000 5
b110110000100000000000000000000 n
b100 ,
b100 o
b100 q
b1 $
1!
#30000
0!
#35000
b10001 &
b10001 w
b0 ?
b0 B
b0 a
1(
1=
b10001 i
b10001 u
b0 t
b1111 R
b1100 -
b1100 p
b111100000100010000000000000000 5
b111100000100010000000000000000 n
b1000 ,
b1000 o
b1000 q
b10 $
1!
#40000
0!
#45000
b1000000000 E
b11 ?
b11 B
b11 a
1(
1=
b1000000000 '
b1000 k
b10001 t
b1101 R
b10000 -
b10000 p
b110110001100010000001000000000 5
b110110001100010000001000000000 n
b1100 ,
b1100 o
b1100 q
b11 $
1!
#50000
0!
#55000
b10010 &
b10010 w
b0 E
b0 ?
b0 B
b0 a
1(
1=
b0 '
b0 k
b10010 i
b10010 u
b0 t
b1111 R
b10100 -
b10100 p
b111100000100100000000000000000 5
b111100000100100000000000000000 n
b10000 ,
b10000 o
b10000 q
b100 $
1!
#60000
0!
#65000
b100000000 E
b11 ?
b11 B
b11 a
1(
1=
b100000000 '
b100 k
b10010 t
b1101 R
b11000 -
b11000 p
b110110010100100000000100000000 5
b110110010100100000000100000000 n
b10100 ,
b10100 o
b10100 q
b101 $
1!
#70000
0!
#75000
bx j
bx v
bx 3
bx d
b1010 &
b1010 w
b1100100 E
12
11
b0 ?
b0 B
b0 a
1(
1=
b1100100 '
b100100 A
b1 k
b1010 i
b1010 u
b100100 Q
b100011 R
b11100 -
b11100 p
b10001110010010100000000001100100 5
b10001110010010100000000001100100 n
b11000 ,
b11000 o
b11000 q
b110 $
1!
#80000
0!
#85000
bz 3
bz d
b1000 &
b1000 w
b0 E
02
1(
01
1=
b0 '
b0 A
b0 k
b1000 i
b1000 u
b0 t
b0 Q
b1000 R
b100000 -
b100000 p
b100000000010000000000000000000 5
b100000000010000000000000000000 n
b11100 ,
b11100 o
b11100 q
b111 $
1!
#90000
0!
#95000
b1001 &
b1001 w
b1001 i
b1001 u
b100100 -
b100100 p
b100000000010010000000000000000 5
b100000000010010000000000000000 n
b100000 ,
b100000 o
b100000 q
b1000 $
1!
#100000
0!
#105000
bx E
b1000 &
b1000 w
0(
0=
b1000 i
b1000 u
b1000 t
b110000 R
b101000 -
b101000 p
b11000001000010000000000000000000 5
b11000001000010000000000000000000 n
b100100 ,
b100100 o
b100100 q
b1001 $
1!
#110000
0!
#115000
b0 j
b0 v
1%
b0 >
b0 M
b0 b
b1xxxxxxxxxxxxxxxxxxxxxxx K
b1xxxxxxxxxxxxxxxxxxxxxxx J
b0 &
b0 w
b1111 @
b1111 C
b1111 D
16
1:
b10000110 '
b110 A
b10 k
b0 i
b0 u
b10000 t
b110 Q
b10001 R
b101100 -
b101100 p
b1000110000000000000000010000110 5
b1000110000000000000000010000110 n
b101000 ,
b101000 o
b101000 q
b1010 $
1!
#120000
0!
#125000
bx j
bx v
x%
bx >
bx M
bx b
b1010 &
b1010 w
b1100 @
b1100 C
b1100 D
1:
16
b10 '
b10 A
b0 k
b1010 i
b1010 u
b10 Q
b110000 -
b110000 p
b1000110000010100000000000000010 5
b1000110000010100000000000000010 n
b101100 ,
b101100 o
b101100 q
b1011 $
1!
#130000
0!
#135000
b0 &
b0 w
b0 @
b0 C
b0 D
1:
16
b100001101 '
b1101 A
b100 k
bx 8
bx g
b0 i
b0 u
b1101 Q
b110100 -
b110100 p
b1000110000000000000000100001101 5
b1000110000000000000000100001101 n
bx 9
bx f
b110000 ,
b110000 o
b110000 q
b1100 $
1!
#140000
0!
#145000
b10 &
b10 w
b10 @
b10 C
b10 D
1.
1(
0:
06
b0 '
b0 A
b0 k
b0 8
b0 g
b10 i
b10 u
b0 t
b0 Q
b111000 -
b111000 p
b1000100000000100000000000000000 5
b1000100000000100000000000000000 n
b110100 ,
b110100 o
b110100 q
b1101 $
1!
#150000
0!
#155000
b1011 &
b1011 w
b0 @
b0 C
b0 D
b10 ?
b10 B
b10 a
1)
0.
1(
b101100000100001 '
b100001 A
b0 9
b0 f
b1011 h
b100001 Q
b0 R
b111100 -
b111100 p
b100101100000100001 5
b100101100000100001 n
b111000 ,
b111000 o
b111000 q
b1110 $
1!
#160000
0!
#165000
b1010 &
b1010 w
b1000 @
b1000 C
b1000 D
b10 ?
b10 B
b10 a
1(
1)
b101000011000000 '
b0 A
b11 k
b1010 h
b0 Q
b1000000 -
b1000000 p
b100101000011000000 5
b100101000011000000 n
b111100 ,
b111100 o
b111100 q
b1111 $
1!
#170000
0!
#175000
b101010011000000 '
b10011 k
b1000100 -
b1000100 p
b100101010011000000 5
b100101010011000000 n
b1000000 ,
b1000000 o
b1000000 q
b10000 $
1!
#180000
0!
#185000
b10 @
b10 C
b10 D
b10 ?
b10 B
b10 a
1(
1)
b101000000100000 '
b100000 A
b0 k
b1000 i
b1000 u
b1010 t
b100000 Q
b1001000 -
b1001000 p
b1010010000101000000100000 5
b1010010000101000000100000 n
b1000100 ,
b1000100 o
b1000100 q
b10001 $
1!
#190000
0!
#195000
b10001 i
b10001 u
b1001100 -
b1001100 p
b1010100010101000000100000 5
b1010100010101000000100000 n
b1001000 ,
b1001000 o
b1001000 q
b10010 $
1!
#200000
0!
